npgbq/__init__.py
npgbq/connectors/__init__.py
npgbq/connectors/dtype_mapper.py
npgbq/connectors/mysql.py
npgbq/connectors/npmssql.py
npgbq/connectors/postgres.py
npgbq/core/__init__.py
npgbq/core/helper_phone_number_th.py
npgbq/core/log_table_schema.py
npgbq/core/tools.py
npgbq/util/__init__.py
npgbq/util/filebase.py
npgbq-2.1.21.dist-info/LICENSE
npgbq-2.1.21.dist-info/METADATA
npgbq-2.1.21.dist-info/WHEEL
npgbq-2.1.21.dist-info/top_level.txt
npgbq-2.1.21.dist-info/RECORD
